htmlviewPY/__init__.py
htmlviewPY-3.11.0.dist-info/METADATA
htmlviewPY-3.11.0.dist-info/WHEEL
htmlviewPY-3.11.0.dist-info/top_level.txt
htmlviewPY-3.11.0.dist-info/RECORD
