Metadata-Version: 2.1
Name: htmlviewPY
Version: 3.11.0
Summary: View and print the HTML of websites!
Home-page: UNKNOWN
Author: Daniel Duchouquette
Author-email: <danpersonguything@email.com>
License: UNKNOWN
Keywords: python,Simple,HTML,view,webscraping
Platform: UNKNOWN
Classifier: Development Status :: 3 - Alpha
Classifier: Intended Audience :: Education
Classifier: Programming Language :: Python :: 2
Classifier: Programming Language :: Python :: 3
Classifier: Operating System :: MacOS :: MacOS X
Classifier: Operating System :: Microsoft :: Windows
